[{"id":1,"name":"base","formtabs":"[{\"MIGX_id\":30,\"caption\":\"\\u041d\\u0430\\u0441\\u0442\\u0440\\u043e\\u0439\\u043a\\u0438 \\u0441\\u0435\\u043a\\u0446\\u0438\\u0438\",\"print_before_tabs\":\"0\",\"fields\":[{\"MIGX_id\":179,\"field\":\"id\",\"caption\":\"ID\",\"description\":\"\\u0434\\u043e\\u043b\\u0436\\u0435\\u043d \\u0431\\u044b\\u0442\\u044c \\u0443\\u043d\\u0438\\u043a\\u0430\\u043b\\u044c\\u043d\\u044b\\u043c \\u0432 \\u043f\\u0440\\u0435\\u0434\\u0435\\u043b\\u0430\\u0445 \\u043e\\u0434\\u043d\\u043e\\u0439 \\u043a\\u043e\\u043d\\u0444\\u0438\\u0433\\u0443\\u0440\\u0430\\u0446\\u0438\\u0438\\\/\\u0441\\u0442\\u0440\\u0430\\u043d\\u0438\\u0446\\u044b\\\/\\u0440\\u0435\\u0441\\u0443\\u0440\\u0441\\u0430\\\/\\u0434\\u043e\\u043a\\u0443\\u043c\\u0435\\u043d\\u0442\\u0430\",\"description_is_code\":\"0\",\"inputTV\":\"\",\"inputTVtype\":\"\",\"validation\":\"\",\"configs\":\"\",\"restrictive_condition\":\"\",\"display\":\"\",\"sourceFrom\":\"config\",\"sources\":\"\",\"inputOptionValues\":\"\",\"default\":\"\",\"useDefaultIfEmpty\":\"0\",\"pos\":1},{\"MIGX_id\":180,\"field\":\"section_name\",\"caption\":\"\\u041d\\u0430\\u0437\\u0432\\u0430\\u043d\\u0438\\u0435\",\"description\":\"\\u043b\\u044e\\u0431\\u043e\\u0435 \\u043f\\u043e\\u043d\\u044f\\u0442\\u043d\\u043e\\u0435 \\u043d\\u0430\\u0437\\u0432\\u0430\\u043d\\u0438\\u0435\",\"description_is_code\":\"0\",\"inputTV\":\"\",\"inputTVtype\":\"\",\"validation\":\"\",\"configs\":\"\",\"restrictive_condition\":\"\",\"display\":\"\",\"sourceFrom\":\"config\",\"sources\":\"\",\"inputOptionValues\":\"\",\"default\":\"\",\"useDefaultIfEmpty\":\"0\",\"pos\":2},{\"MIGX_id\":181,\"field\":\"file_name\",\"caption\":\"\\u0418\\u043c\\u044f \\u0444\\u0430\\u0439\\u043b\\u0430 \\u0441\\u0435\\u043a\\u0446\\u0438\\u0438\",\"description\":\"\\u0440\\u0435\\u0434\\u0430\\u043a\\u0442\\u0438\\u0440\\u043e\\u0432\\u0430\\u0442\\u044c \\u0442\\u043e\\u043b\\u044c\\u043a\\u043e \\u0432 \\u0441\\u043b\\u0443\\u0447\\u0430\\u0435 \\u043f\\u0435\\u0440\\u0435\\u0438\\u043c\\u0435\\u043d\\u043e\\u0432\\u0430\\u043d\\u0438\\u044f \\u0444\\u0430\\u0439\\u043b\\u0430\",\"description_is_code\":\"0\",\"inputTV\":\"\",\"inputTVtype\":\"file\",\"validation\":\"\",\"configs\":\"\",\"restrictive_condition\":\"\",\"display\":\"\",\"sourceFrom\":\"config\",\"sources\":\"\",\"inputOptionValues\":\"\",\"default\":\"\",\"useDefaultIfEmpty\":\"0\",\"pos\":3},{\"MIGX_id\":182,\"field\":\"pt_lg\",\"caption\":\"Padding top (PC)\",\"description\":\"\\u0447\\u0438\\u0441\\u043b\\u043e \\u043e\\u0442 0 \\u0434\\u043e 100 \\u0441 \\u0448\\u0430\\u0433\\u043e\\u043c 5\",\"description_is_code\":\"0\",\"inputTV\":\"\",\"inputTVtype\":\"number\",\"validation\":\"\",\"configs\":\"\",\"restrictive_condition\":\"\",\"display\":\"\",\"sourceFrom\":\"config\",\"sources\":\"\",\"inputOptionValues\":\"\",\"default\":90,\"useDefaultIfEmpty\":1,\"pos\":4},{\"MIGX_id\":183,\"field\":\"pb_lg\",\"caption\":\"Padding bottom (PC)\",\"description\":\"\\u0447\\u0438\\u0441\\u043b\\u043e \\u043e\\u0442 0 \\u0434\\u043e 100 \\u0441 \\u0448\\u0430\\u0433\\u043e\\u043c 5\",\"description_is_code\":\"0\",\"inputTV\":\"\",\"inputTVtype\":\"number\",\"validation\":\"\",\"configs\":\"\",\"restrictive_condition\":\"\",\"display\":\"\",\"sourceFrom\":\"config\",\"sources\":\"\",\"inputOptionValues\":\"\",\"default\":90,\"useDefaultIfEmpty\":1,\"pos\":5},{\"MIGX_id\":184,\"field\":\"pt\",\"caption\":\"Padding top (MOB)\",\"description\":\"\\u0447\\u0438\\u0441\\u043b\\u043e \\u043e\\u0442 0 \\u0434\\u043e 100 \\u0441 \\u0448\\u0430\\u0433\\u043e\\u043c 5\",\"description_is_code\":\"0\",\"inputTV\":\"\",\"inputTVtype\":\"number\",\"validation\":\"\",\"configs\":\"\",\"restrictive_condition\":\"\",\"display\":\"\",\"sourceFrom\":\"config\",\"sources\":\"\",\"inputOptionValues\":\"\",\"default\":45,\"useDefaultIfEmpty\":1,\"pos\":6},{\"MIGX_id\":185,\"field\":\"pb\",\"caption\":\"Padding bottom (MOB)\",\"description\":\"\\u0447\\u0438\\u0441\\u043b\\u043e \\u043e\\u0442 0 \\u0434\\u043e 100 \\u0441 \\u0448\\u0430\\u0433\\u043e\\u043c 5\",\"description_is_code\":\"0\",\"inputTV\":\"\",\"inputTVtype\":\"number\",\"validation\":\"\",\"configs\":\"\",\"restrictive_condition\":\"\",\"display\":\"\",\"sourceFrom\":\"config\",\"sources\":\"\",\"inputOptionValues\":\"\",\"default\":45,\"useDefaultIfEmpty\":1,\"pos\":7},{\"MIGX_id\":186,\"field\":\"hide_section\",\"caption\":\"\\u0421\\u043a\\u0440\\u044b\\u0442\\u044c \\u0441\\u0435\\u043a\\u0446\\u0438\\u044e?\",\"description\":\"\",\"description_is_code\":\"0\",\"inputTV\":\"\",\"inputTVtype\":\"checkbox\",\"validation\":\"\",\"configs\":\"\",\"restrictive_condition\":\"\",\"display\":\"\",\"sourceFrom\":\"config\",\"sources\":\"\",\"inputOptionValues\":\"\\u0414\\u0430==1\",\"default\":\"\",\"useDefaultIfEmpty\":\"0\",\"pos\":8},{\"MIGX_id\":187,\"field\":\"copy_from_origin\",\"caption\":\"\\u041a\\u043e\\u043f\\u0438\\u0440\\u043e\\u0432\\u0430\\u0442\\u044c \\u0441\\u043e\\u0434\\u0435\\u0440\\u0436\\u0438\\u043c\\u043e\\u0435 \\u0438\\u0437 \\u0422\\u0438\\u043f\\u043e\\u0432 \\u0441\\u0442\\u0440\\u0430\\u043d\\u0438\\u0446?\",\"description\":\"\",\"description_is_code\":\"0\",\"inputTV\":\"\",\"inputTVtype\":\"checkbox\",\"validation\":\"\",\"configs\":\"\",\"restrictive_condition\":\"\",\"display\":\"\",\"sourceFrom\":\"config\",\"sources\":\"\",\"inputOptionValues\":\"\\u0414\\u0430==1\",\"default\":\"\",\"useDefaultIfEmpty\":\"0\",\"pos\":9},{\"MIGX_id\":188,\"field\":\"is_static\",\"caption\":\"\\u042d\\u0442\\u043e \\u0441\\u0442\\u0430\\u0442\\u0438\\u0447\\u043d\\u0430\\u044f \\u0441\\u0435\\u043a\\u0446\\u0438\\u044f?\",\"description\":\"\",\"description_is_code\":\"0\",\"inputTV\":\"\",\"inputTVtype\":\"checkbox\",\"validation\":\"\",\"configs\":\"\",\"restrictive_condition\":\"\",\"display\":\"\",\"sourceFrom\":\"config\",\"sources\":\"\",\"inputOptionValues\":\"\\u0414\\u0430==1\",\"default\":\"\",\"useDefaultIfEmpty\":\"0\",\"pos\":10},{\"MIGX_id\":257,\"field\":\"position\",\"caption\":\"\\u041f\\u043e\\u0440\\u044f\\u0434\\u043a\\u043e\\u0432\\u044b\\u0439 \\u043d\\u043e\\u043c\\u0435\\u0440 \\u043d\\u0430 \\u0441\\u0442\\u0440\\u0430\\u043d\\u0438\\u0446\\u0435\",\"description\":\"\",\"description_is_code\":\"0\",\"inputTV\":\"\",\"inputTVtype\":\"\",\"validation\":\"\",\"configs\":\"\",\"restrictive_condition\":\"\",\"display\":\"\",\"sourceFrom\":\"config\",\"sources\":\"\",\"inputOptionValues\":\"\",\"default\":\"\",\"useDefaultIfEmpty\":\"0\",\"pos\":11}],\"pos\":1},{\"MIGX_id\":41,\"caption\":\"\\u0421\\u043e\\u0434\\u0435\\u0440\\u0436\\u0438\\u043c\\u043e\\u0435 \\u0441\\u0435\\u043a\\u0446\\u0438\\u0438\",\"print_before_tabs\":\"0\",\"fields\":[{\"MIGX_id\":258,\"field\":\"title\",\"caption\":\"\\u0417\\u0430\\u0433\\u043e\\u043b\\u043e\\u0432\\u043e\\u043a\",\"description\":\"\",\"description_is_code\":\"0\",\"inputTV\":\"\",\"inputTVtype\":\"textarea\",\"validation\":\"\",\"configs\":\"\",\"restrictive_condition\":\"\",\"display\":\"\",\"sourceFrom\":\"config\",\"sources\":\"\",\"inputOptionValues\":\"\",\"default\":\"\",\"useDefaultIfEmpty\":\"0\",\"pos\":1},{\"MIGX_id\":259,\"field\":\"subtitle\",\"caption\":\"\\u041f\\u043e\\u0434\\u0437\\u0430\\u0433\\u043e\\u043b\\u043e\\u0432\\u043e\\u043a\",\"description\":\"\",\"description_is_code\":\"0\",\"inputTV\":\"\",\"inputTVtype\":\"textarea\",\"validation\":\"\",\"configs\":\"\",\"restrictive_condition\":\"\",\"display\":\"\",\"sourceFrom\":\"config\",\"sources\":\"\",\"inputOptionValues\":\"\",\"default\":\"\",\"useDefaultIfEmpty\":\"0\",\"pos\":2},{\"MIGX_id\":260,\"field\":\"content\",\"caption\":\"\\u0422\\u0435\\u043a\\u0441\\u0442\",\"description\":\"\\u0435\\u0441\\u043b\\u0438 \\u043d\\u0435 \\u0437\\u0430\\u043f\\u043e\\u043b\\u043d\\u0435\\u043d\\u043e - \\u043d\\u0435 \\u0432\\u044b\\u0432\\u043e\\u0434\\u0438\\u0442\\u0441\\u044f\",\"description_is_code\":\"0\",\"inputTV\":\"\",\"inputTVtype\":\"textarea\",\"validation\":\"\",\"configs\":\"\",\"restrictive_condition\":\"\",\"display\":\"\",\"sourceFrom\":\"config\",\"sources\":\"\",\"inputOptionValues\":\"\",\"default\":\"\",\"useDefaultIfEmpty\":\"0\",\"pos\":3},{\"MIGX_id\":261,\"field\":\"btn_text\",\"caption\":\"\\u0422\\u0435\\u043a\\u0441\\u0442 \\u043a\\u043d\\u043e\\u043f\\u043a\\u0438\",\"description\":\"\\u0437\\u0430\\u043f\\u043e\\u043b\\u043d\\u044f\\u0435\\u0442\\u0441\\u044f \\u0435\\u0441\\u043b\\u0438 \\u0435\\u0441\\u0442\\u044c \\u043a\\u043d\\u043e\\u043f\\u043a\\u0430, \\u0435\\u0441\\u043b\\u0438 \\u043d\\u0435 \\u0437\\u0430\\u043f\\u043e\\u043b\\u043d\\u0435\\u043d\\u043e - \\u043d\\u0435 \\u0432\\u044b\\u0432\\u043e\\u0434\\u0438\\u0442\\u0441\\u044f.\",\"description_is_code\":\"0\",\"inputTV\":\"\",\"inputTVtype\":\"\",\"validation\":\"\",\"configs\":\"\",\"restrictive_condition\":\"\",\"display\":\"\",\"sourceFrom\":\"config\",\"sources\":\"\",\"inputOptionValues\":\"\",\"default\":\"\",\"useDefaultIfEmpty\":\"0\",\"pos\":4},{\"MIGX_id\":262,\"field\":\"target\",\"caption\":\"\\u0426\\u0435\\u043b\\u0435\\u0432\\u043e\\u0435 \\u043e\\u043a\\u043d\\u043e\",\"description\":\"ID \\u043c\\u043e\\u0434\\u0430\\u043b\\u044c\\u043d\\u043e\\u0433\\u043e \\u043e\\u043a\\u043d\\u0430 \\u0432 \\u0432\\u0438\\u0434\\u0435 \\u044f\\u043a\\u043e\\u0440\\u044f \\u0438\\u043b\\u0438 \\u0441\\u0441\\u044b\\u043b\\u043a\\u0430 \\u043d\\u0430 \\u0434\\u0440\\u0443\\u0433\\u0443\\u044e \\u0441\\u0442\\u0440\\u0430\\u043d\\u0438\\u0446\\u0443 \\u0438\\u043b\\u0438 \\u0441\\u0430\\u0439\\u0442\",\"description_is_code\":\"0\",\"inputTV\":\"\",\"inputTVtype\":\"\",\"validation\":\"\",\"configs\":\"\",\"restrictive_condition\":\"\",\"display\":\"\",\"sourceFrom\":\"config\",\"sources\":\"\",\"inputOptionValues\":\"\",\"default\":\"\",\"useDefaultIfEmpty\":\"0\",\"pos\":5},{\"MIGX_id\":263,\"field\":\"list_double\",\"caption\":\"\\u0414\\u0432\\u043e\\u0439\\u043d\\u043e\\u0439 \\u0441\\u043f\\u0438\\u0441\\u043e\\u043a\",\"description\":\"\",\"description_is_code\":\"0\",\"inputTV\":\"\",\"inputTVtype\":\"migx\",\"validation\":\"\",\"configs\":\"list_double\",\"restrictive_condition\":\"\",\"display\":\"\",\"sourceFrom\":\"config\",\"sources\":\"\",\"inputOptionValues\":\"\",\"default\":\"\",\"useDefaultIfEmpty\":\"0\",\"pos\":6},{\"MIGX_id\":264,\"field\":\"list_triple\",\"caption\":\"\\u0422\\u0440\\u043e\\u0439\\u043d\\u043e\\u0439 \\u0441\\u043f\\u0438\\u0441\\u043e\\u043a\",\"description\":\"\",\"description_is_code\":\"0\",\"inputTV\":\"\",\"inputTVtype\":\"migx\",\"validation\":\"\",\"configs\":\"list_triple\",\"restrictive_condition\":\"\",\"display\":\"\",\"sourceFrom\":\"config\",\"sources\":\"\",\"inputOptionValues\":\"\",\"default\":\"\",\"useDefaultIfEmpty\":\"0\",\"pos\":7},{\"MIGX_id\":265,\"field\":\"list_triple_img\",\"caption\":\"\\u0422\\u0440\\u043e\\u0439\\u043d\\u043e\\u0439 \\u0441\\u043f\\u0438\\u0441\\u043e\\u043a \\u0441 \\u043a\\u0430\\u0440\\u0442\\u0438\\u043d\\u043a\\u043e\\u0439\",\"description\":\"\",\"description_is_code\":\"0\",\"inputTV\":\"\",\"inputTVtype\":\"migx\",\"validation\":\"\",\"configs\":\"list_triple_img\",\"restrictive_condition\":\"\",\"display\":\"\",\"sourceFrom\":\"config\",\"sources\":\"\",\"inputOptionValues\":\"\",\"default\":\"\",\"useDefaultIfEmpty\":\"0\",\"pos\":8},{\"MIGX_id\":266,\"field\":\"list_double_img\",\"caption\":\"\\u0414\\u0432\\u043e\\u0439\\u043d\\u043e\\u0439 \\u0441\\u043f\\u0438\\u0441\\u043e\\u043a \\u0441 \\u043a\\u0430\\u0440\\u0442\\u0438\\u043d\\u043a\\u043e\\u0439\",\"description\":\"\",\"description_is_code\":\"0\",\"inputTV\":\"\",\"inputTVtype\":\"migx\",\"validation\":\"\",\"configs\":\"list_double_img\",\"restrictive_condition\":\"\",\"display\":\"\",\"sourceFrom\":\"config\",\"sources\":\"\",\"inputOptionValues\":\"\",\"default\":\"\",\"useDefaultIfEmpty\":\"0\",\"pos\":9},{\"MIGX_id\":267,\"field\":\"list_simple\",\"caption\":\"\\u041f\\u0440\\u043e\\u0441\\u0442\\u043e\\u0439 \\u0441\\u043f\\u0438\\u0441\\u043e\\u043a\",\"description\":\"\",\"description_is_code\":\"0\",\"inputTV\":\"\",\"inputTVtype\":\"migx\",\"validation\":\"\",\"configs\":\"list_simple\",\"restrictive_condition\":\"\",\"display\":\"\",\"sourceFrom\":\"config\",\"sources\":\"\",\"inputOptionValues\":\"\",\"default\":\"\",\"useDefaultIfEmpty\":\"0\",\"pos\":10},{\"MIGX_id\":268,\"field\":\"img\",\"caption\":\"\\u041a\\u0430\\u0440\\u0442\\u0438\\u043d\\u043a\\u0430\",\"description\":\"\",\"description_is_code\":\"0\",\"inputTV\":\"\",\"inputTVtype\":\"image\",\"validation\":\"\",\"configs\":\"\",\"restrictive_condition\":\"\",\"display\":\"\",\"sourceFrom\":\"config\",\"sources\":\"\",\"inputOptionValues\":\"\",\"default\":\"\",\"useDefaultIfEmpty\":\"0\",\"pos\":11},{\"MIGX_id\":269,\"field\":\"img_mob\",\"caption\":\"\\u041a\\u0430\\u0440\\u0442\\u0438\\u043d\\u043a\\u0430 \\u0434\\u043b\\u044f \\u043c\\u043e\\u0431\\u0438\\u043b\\u044c\\u043d\\u044b\\u0445\",\"description\":\"\",\"description_is_code\":\"0\",\"inputTV\":\"\",\"inputTVtype\":\"image\",\"validation\":\"\",\"configs\":\"\",\"restrictive_condition\":\"\",\"display\":\"\",\"sourceFrom\":\"config\",\"sources\":\"\",\"inputOptionValues\":\"\",\"default\":\"\",\"useDefaultIfEmpty\":\"0\",\"pos\":12},{\"MIGX_id\":270,\"field\":\"preview\",\"caption\":\"\\u041f\\u0440\\u0435\\u0432\\u044c\\u044e\",\"description\":\"\",\"description_is_code\":\"0\",\"inputTV\":\"\",\"inputTVtype\":\"image\",\"validation\":\"\",\"configs\":\"\",\"restrictive_condition\":\"\",\"display\":\"\",\"sourceFrom\":\"config\",\"sources\":\"\",\"inputOptionValues\":\"\",\"default\":\"\",\"useDefaultIfEmpty\":\"0\",\"pos\":13},{\"MIGX_id\":271,\"field\":\"resources\",\"caption\":\"ID \\u0440\\u0435\\u0441\\u0443\\u0440\\u0441\\u043e\\u0432\",\"description\":\"\",\"description_is_code\":\"0\",\"inputTV\":\"\",\"inputTVtype\":\"\",\"validation\":\"\",\"configs\":\"\",\"restrictive_condition\":\"\",\"display\":\"\",\"sourceFrom\":\"config\",\"sources\":\"\",\"inputOptionValues\":\"\",\"default\":\"\",\"useDefaultIfEmpty\":\"0\",\"pos\":14},{\"MIGX_id\":272,\"field\":\"limit\",\"caption\":\"\\u041b\\u0438\\u043c\\u0438\\u0442\",\"description\":\"\",\"description_is_code\":\"0\",\"inputTV\":\"\",\"inputTVtype\":\"number\",\"validation\":\"\",\"configs\":\"\",\"restrictive_condition\":\"\",\"display\":\"\",\"sourceFrom\":\"config\",\"sources\":\"\",\"inputOptionValues\":\"\",\"default\":\"\",\"useDefaultIfEmpty\":\"0\",\"pos\":15},{\"MIGX_id\":273,\"field\":\"list_simple_img\",\"caption\":\"C\\u043f\\u0438\\u0441\\u043e\\u043a \\u0441 \\u043a\\u0430\\u0440\\u0442\\u0438\\u043d\\u043a\\u043e\\u0439\",\"description\":\"\",\"description_is_code\":\"0\",\"inputTV\":\"\",\"inputTVtype\":\"migx\",\"validation\":\"\",\"configs\":\"list_simple_img\",\"restrictive_condition\":\"\",\"display\":\"\",\"sourceFrom\":\"config\",\"sources\":\"\",\"inputOptionValues\":\"\",\"default\":\"\",\"useDefaultIfEmpty\":\"0\",\"pos\":16},{\"MIGX_id\":274,\"field\":\"img_w\",\"caption\":\"\\u0428\\u0438\\u0440\\u0438\\u043d\\u0430 \\u043a\\u0430\\u0440\\u0442\\u0438\\u043d\\u043a\\u0438\",\"description\":\"\",\"description_is_code\":\"0\",\"inputTV\":\"\",\"inputTVtype\":\"number\",\"validation\":\"\",\"configs\":\"\",\"restrictive_condition\":\"\",\"display\":\"\",\"sourceFrom\":\"config\",\"sources\":\"\",\"inputOptionValues\":\"\",\"default\":\"\",\"useDefaultIfEmpty\":\"0\",\"pos\":17},{\"MIGX_id\":275,\"field\":\"img_h\",\"caption\":\"\\u0412\\u044b\\u0441\\u043e\\u0442\\u0430 \\u043a\\u0430\\u0440\\u0442\\u0438\\u043d\\u043a\\u0438\",\"description\":\"\",\"description_is_code\":\"0\",\"inputTV\":\"\",\"inputTVtype\":\"number\",\"validation\":\"\",\"configs\":\"\",\"restrictive_condition\":\"\",\"display\":\"\",\"sourceFrom\":\"config\",\"sources\":\"\",\"inputOptionValues\":\"\",\"default\":\"\",\"useDefaultIfEmpty\":\"0\",\"pos\":18},{\"MIGX_id\":276,\"field\":\"img_mob_w\",\"caption\":\"\\u0428\\u0438\\u0440\\u0438\\u043d\\u0430 \\u043a\\u0430\\u0440\\u0442\\u0438\\u043d\\u043a\\u0438 \\u0434\\u043b\\u044f \\u043c\\u043e\\u0431\\u0438\\u043b\\u044c\\u043d\\u044b\\u0445\",\"description\":\"\",\"description_is_code\":\"0\",\"inputTV\":\"\",\"inputTVtype\":\"number\",\"validation\":\"\",\"configs\":\"\",\"restrictive_condition\":\"\",\"display\":\"\",\"sourceFrom\":\"config\",\"sources\":\"\",\"inputOptionValues\":\"\",\"default\":\"\",\"useDefaultIfEmpty\":\"0\",\"pos\":19},{\"MIGX_id\":277,\"field\":\"img_mob_h\",\"caption\":\"\\u0412\\u044b\\u0441\\u043e\\u0442\\u0430 \\u043a\\u0430\\u0440\\u0442\\u0438\\u043d\\u043a\\u0438 \\u0434\\u043b\\u044f \\u043c\\u043e\\u0431\\u0438\\u043b\\u044c\\u043d\\u044b\\u0445\",\"description\":\"\",\"description_is_code\":\"0\",\"inputTV\":\"\",\"inputTVtype\":\"number\",\"validation\":\"\",\"configs\":\"\",\"restrictive_condition\":\"\",\"display\":\"\",\"sourceFrom\":\"config\",\"sources\":\"\",\"inputOptionValues\":\"\",\"default\":\"\",\"useDefaultIfEmpty\":\"0\",\"pos\":20},{\"MIGX_id\":278,\"field\":\"bg_img\",\"caption\":\"\\u0424\\u043e\\u043d\\u043e\\u0432\\u0430\\u044f \\u043a\\u0430\\u0440\\u0442\\u0438\\u043d\\u043a\\u0430\",\"description\":\"\",\"description_is_code\":\"0\",\"inputTV\":\"\",\"inputTVtype\":\"image\",\"validation\":\"\",\"configs\":\"\",\"restrictive_condition\":\"\",\"display\":\"\",\"sourceFrom\":\"config\",\"sources\":\"\",\"inputOptionValues\":\"\",\"default\":\"\",\"useDefaultIfEmpty\":\"0\",\"pos\":21},{\"MIGX_id\":279,\"field\":\"list_of_lists\",\"caption\":\"\\u0421\\u043f\\u0438\\u0441\\u043e\\u043a \\u0441\\u043f\\u0438\\u0441\\u043a\\u043e\\u0432\",\"description\":\"\",\"description_is_code\":\"0\",\"inputTV\":\"\",\"inputTVtype\":\"migx\",\"validation\":\"\",\"configs\":\"list_of_lists\",\"restrictive_condition\":\"\",\"display\":\"\",\"sourceFrom\":\"config\",\"sources\":\"\",\"inputOptionValues\":\"\",\"default\":\"\",\"useDefaultIfEmpty\":\"0\",\"pos\":22}],\"pos\":2}]","contextmenus":"","actionbuttons":"","columnbuttons":"","filters":"","extended":{"migx_add":"","disable_add_item":"","add_items_directly":"","formcaption":"","update_win_title":"","win_id":"","maxRecords":"","addNewItemAt":"bottom","media_source_id":"","multiple_formtabs":"","multiple_formtabs_label":"","multiple_formtabs_field":"","multiple_formtabs_optionstext":"Базовая секция","multiple_formtabs_optionsvalue":"","actionbuttonsperrow":"4","winbuttonslist":"","extrahandlers":"","filtersperrow":"4","packageName":"","classname":"","task":"","getlistsort":"","getlistsortdir":"","sortconfig":"","gridpagesize":"","use_custom_prefix":"0","prefix":"","grid":"","gridload_mode":"1","check_resid":"1","check_resid_TV":"","join_alias":"","has_jointable":"yes","getlistwhere":"","joins":"","hooksnippets":"","cmpmaincaption":"","cmptabcaption":"","cmptabdescription":"","cmptabcontroller":"","winbuttons":"","onsubmitsuccess":"","submitparams":""},"permissions":{"apiaccess":"","view":"","list":"","save":"","create":"","remove":"","delete":"","publish":"","unpublish":"","viewdeleted":"","viewunpublished":""},"fieldpermissions":"","columns":"[{\"MIGX_id\":2,\"header\":\"\\u041d\\u0430\\u0437\\u0432\\u0430\\u043d\\u0438\\u0435 \\u0441\\u0435\\u043a\\u0446\\u0438\\u0438\",\"dataIndex\":\"section_name\",\"width\":\"\",\"sortable\":\"false\",\"show_in_grid\":1,\"customrenderer\":\"\",\"renderer\":\"\",\"clickaction\":\"\",\"selectorconfig\":\"\",\"renderchunktpl\":\"\",\"renderoptions\":\"\",\"editor\":\"\"}]","createdby":1,"createdon":"2022-04-04 13:58:32","editedby":1,"editedon":"2023-04-17 16:41:19","deleted":0,"deletedon":null,"deletedby":0,"published":1,"publishedon":null,"publishedby":0,"category":""},{"id":2,"name":"config","formtabs":"","contextmenus":"","actionbuttons":"","columnbuttons":"","filters":"","extended":{"migx_add":"","disable_add_item":"","add_items_directly":"","formcaption":"","update_win_title":"","win_id":"","maxRecords":"","addNewItemAt":"bottom","media_source_id":"","multiple_formtabs":"1||50","multiple_formtabs_label":"Выберите секцию","multiple_formtabs_field":"","multiple_formtabs_optionstext":"","multiple_formtabs_optionsvalue":"","actionbuttonsperrow":"4","winbuttonslist":"","extrahandlers":"","filtersperrow":"4","packageName":"","classname":"","task":"","getlistsort":"","getlistsortdir":"","sortconfig":"","gridpagesize":"","use_custom_prefix":"0","prefix":"","grid":"","gridload_mode":"1","check_resid":"1","check_resid_TV":"","join_alias":"","has_jointable":"yes","getlistwhere":"","joins":"","hooksnippets":"","cmpmaincaption":"","cmptabcaption":"","cmptabdescription":"","cmptabcontroller":"","winbuttons":"","onsubmitsuccess":"","submitparams":""},"permissions":{"apiaccess":"","view":"","list":"","save":"","create":"","remove":"","delete":"","publish":"","unpublish":"","viewdeleted":"","viewunpublished":""},"fieldpermissions":"","columns":"[{\"MIGX_id\":1,\"header\":\"\\u041d\\u0430\\u0437\\u0432\\u0430\\u043d\\u0438\\u0435 \\u0441\\u0435\\u043a\\u0446\\u0438\\u0438\",\"dataIndex\":\"section_name\",\"width\":\"\",\"sortable\":\"false\",\"show_in_grid\":1,\"customrenderer\":\"\",\"renderer\":\"\",\"clickaction\":\"\",\"selectorconfig\":\"\",\"renderchunktpl\":\"\",\"renderoptions\":\"\",\"editor\":\"\"},{\"MIGX_id\":2,\"header\":\"\\u0418\\u043c\\u044f \\u0444\\u0430\\u0439\\u043b\\u0430\",\"dataIndex\":\"file_name_vis\",\"width\":\"\",\"sortable\":\"false\",\"show_in_grid\":1,\"customrenderer\":\"\",\"renderer\":\"this.renderChunk\",\"clickaction\":\"\",\"selectorconfig\":\"\",\"renderchunktpl\":\"<a target=\\\"_blank\\\" href=\\\"[[++site_url]]manager\\\/?a=system\\\/file\\\/edit&file=[[+file_name]]&wctx=mgr&source=1\\\">[[+file_name]]<\\\/a>\",\"renderoptions\":\"\",\"editor\":\"\"}]","createdby":1,"createdon":"2022-04-04 13:58:46","editedby":1,"editedon":"2023-01-02 21:33:34","deleted":0,"deletedon":null,"deletedby":0,"published":1,"publishedon":null,"publishedby":0,"category":""},{"id":3,"name":"list_triple","formtabs":"[{\"MIGX_id\":17,\"caption\":\"\",\"print_before_tabs\":\"0\",\"fields\":[{\"MIGX_id\":117,\"field\":\"title\",\"caption\":\"\\u0417\\u0430\\u0433\\u043e\\u043b\\u043e\\u0432\\u043e\\u043a\",\"description\":\"\",\"description_is_code\":\"0\",\"inputTV\":\"\",\"inputTVtype\":\"\",\"validation\":\"\",\"configs\":\"\",\"restrictive_condition\":\"\",\"display\":\"\",\"sourceFrom\":\"config\",\"sources\":\"\",\"inputOptionValues\":\"\",\"default\":\"\",\"useDefaultIfEmpty\":\"0\",\"pos\":1},{\"MIGX_id\":118,\"field\":\"subtitle\",\"caption\":\"\\u041f\\u043e\\u0434\\u0437\\u0430\\u0433\\u043e\\u043b\\u043e\\u0432\\u043e\\u043a\",\"description\":\"\",\"description_is_code\":\"0\",\"inputTV\":\"\",\"inputTVtype\":\"\",\"validation\":\"\",\"configs\":\"\",\"restrictive_condition\":\"\",\"display\":\"\",\"sourceFrom\":\"config\",\"sources\":\"\",\"inputOptionValues\":\"\",\"default\":\"\",\"useDefaultIfEmpty\":\"0\",\"pos\":2},{\"MIGX_id\":119,\"field\":\"content\",\"caption\":\"\\u0421\\u043e\\u0434\\u0435\\u0440\\u0436\\u0438\\u043c\\u043e\\u0435\",\"description\":\"\",\"description_is_code\":\"0\",\"inputTV\":\"\",\"inputTVtype\":\"textarea\",\"validation\":\"\",\"configs\":\"\",\"restrictive_condition\":\"\",\"display\":\"\",\"sourceFrom\":\"config\",\"sources\":\"\",\"inputOptionValues\":\"\",\"default\":\"\",\"useDefaultIfEmpty\":\"0\",\"pos\":3}],\"pos\":1}]","contextmenus":"","actionbuttons":"","columnbuttons":"","filters":"","extended":{"migx_add":"","disable_add_item":"","add_items_directly":"","formcaption":"","update_win_title":"","win_id":"","maxRecords":"","addNewItemAt":"bottom","media_source_id":"","multiple_formtabs":"","multiple_formtabs_label":"","multiple_formtabs_field":"","multiple_formtabs_optionstext":"","multiple_formtabs_optionsvalue":"","actionbuttonsperrow":"4","winbuttonslist":"","extrahandlers":"","filtersperrow":"4","packageName":"","classname":"","task":"","getlistsort":"","getlistsortdir":"","sortconfig":"","gridpagesize":"","use_custom_prefix":"0","prefix":"","grid":"","gridload_mode":"1","check_resid":"1","check_resid_TV":"","join_alias":"","has_jointable":"yes","getlistwhere":"","joins":"","hooksnippets":"","cmpmaincaption":"","cmptabcaption":"","cmptabdescription":"","cmptabcontroller":"","winbuttons":"","onsubmitsuccess":"","submitparams":""},"permissions":{"apiaccess":"","view":"","list":"","save":"","create":"","remove":"","delete":"","publish":"","unpublish":"","viewdeleted":"","viewunpublished":""},"fieldpermissions":"","columns":"[{\"MIGX_id\":1,\"header\":\"\\u0417\\u0430\\u0433\\u043e\\u043b\\u043e\\u0432\\u043e\\u043a\",\"dataIndex\":\"title\",\"width\":\"\",\"sortable\":\"false\",\"show_in_grid\":1,\"customrenderer\":\"\",\"renderer\":\"\",\"clickaction\":\"\",\"selectorconfig\":\"\",\"renderchunktpl\":\"\",\"renderoptions\":\"\",\"editor\":\"\"}]","createdby":1,"createdon":"2022-04-04 14:08:18","editedby":1,"editedon":"2022-09-13 11:59:44","deleted":0,"deletedon":null,"deletedby":0,"published":1,"publishedon":null,"publishedby":0,"category":""},{"id":4,"name":"list_double","formtabs":"[{\"MIGX_id\":18,\"caption\":\"\",\"print_before_tabs\":\"0\",\"fields\":[{\"MIGX_id\":120,\"field\":\"title\",\"caption\":\"\\u0417\\u0430\\u0433\\u043e\\u043b\\u043e\\u0432\\u043e\\u043a\",\"description\":\"\",\"description_is_code\":\"0\",\"inputTV\":\"\",\"inputTVtype\":\"\",\"validation\":\"\",\"configs\":\"\",\"restrictive_condition\":\"\",\"display\":\"\",\"sourceFrom\":\"config\",\"sources\":\"\",\"inputOptionValues\":\"\",\"default\":\"\",\"useDefaultIfEmpty\":\"0\",\"pos\":1},{\"MIGX_id\":121,\"field\":\"content\",\"caption\":\"\\u0421\\u043e\\u0434\\u0435\\u0440\\u0436\\u0438\\u043c\\u043e\\u0435\",\"description\":\"\",\"description_is_code\":\"0\",\"inputTV\":\"\",\"inputTVtype\":\"textarea\",\"validation\":\"\",\"configs\":\"\",\"restrictive_condition\":\"\",\"display\":\"\",\"sourceFrom\":\"config\",\"sources\":\"\",\"inputOptionValues\":\"\",\"default\":\"\",\"useDefaultIfEmpty\":\"0\",\"pos\":2}],\"pos\":1}]","contextmenus":"","actionbuttons":"","columnbuttons":"","filters":"","extended":{"migx_add":"","disable_add_item":"","add_items_directly":"","formcaption":"","update_win_title":"","win_id":"","maxRecords":"","addNewItemAt":"bottom","media_source_id":"","multiple_formtabs":"","multiple_formtabs_label":"","multiple_formtabs_field":"","multiple_formtabs_optionstext":"","multiple_formtabs_optionsvalue":"","actionbuttonsperrow":"4","winbuttonslist":"","extrahandlers":"","filtersperrow":"4","packageName":"","classname":"","task":"","getlistsort":"","getlistsortdir":"","sortconfig":"","gridpagesize":"","use_custom_prefix":"0","prefix":"","grid":"","gridload_mode":"1","check_resid":"1","check_resid_TV":"","join_alias":"","has_jointable":"yes","getlistwhere":"","joins":"","hooksnippets":"","cmpmaincaption":"","cmptabcaption":"","cmptabdescription":"","cmptabcontroller":"","winbuttons":"","onsubmitsuccess":"","submitparams":""},"permissions":{"apiaccess":"","view":"","list":"","save":"","create":"","remove":"","delete":"","publish":"","unpublish":"","viewdeleted":"","viewunpublished":""},"fieldpermissions":"","columns":"[{\"MIGX_id\":1,\"header\":\"\\u0417\\u0430\\u0433\\u043e\\u043b\\u043e\\u0432\\u043e\\u043a\",\"dataIndex\":\"title\",\"width\":\"\",\"sortable\":\"false\",\"show_in_grid\":1,\"customrenderer\":\"\",\"renderer\":\"\",\"clickaction\":\"\",\"selectorconfig\":\"\",\"renderchunktpl\":\"\",\"renderoptions\":\"\",\"editor\":\"\"}]","createdby":1,"createdon":"2022-04-04 14:08:30","editedby":1,"editedon":"2022-06-19 19:06:30","deleted":0,"deletedon":null,"deletedby":0,"published":1,"publishedon":null,"publishedby":0,"category":""},{"id":5,"name":"list_simple","formtabs":"[{\"MIGX_id\":19,\"caption\":\"\",\"print_before_tabs\":\"0\",\"fields\":[{\"MIGX_id\":122,\"field\":\"content\",\"caption\":\"\\u0421\\u043e\\u0434\\u0435\\u0440\\u0436\\u0438\\u043c\\u043e\\u0435\",\"description\":\"\",\"description_is_code\":\"0\",\"inputTV\":\"\",\"inputTVtype\":\"textarea\",\"validation\":\"\",\"configs\":\"\",\"restrictive_condition\":\"\",\"display\":\"\",\"sourceFrom\":\"config\",\"sources\":\"\",\"inputOptionValues\":\"\",\"default\":\"\",\"useDefaultIfEmpty\":\"0\",\"pos\":1}],\"pos\":1}]","contextmenus":"","actionbuttons":"","columnbuttons":"","filters":"","extended":{"migx_add":"","disable_add_item":"","add_items_directly":"","formcaption":"","update_win_title":"","win_id":"","maxRecords":"","addNewItemAt":"bottom","media_source_id":"","multiple_formtabs":"","multiple_formtabs_label":"","multiple_formtabs_field":"","multiple_formtabs_optionstext":"","multiple_formtabs_optionsvalue":"","actionbuttonsperrow":4,"winbuttonslist":"","extrahandlers":"","filtersperrow":4,"packageName":"","classname":"","task":"","getlistsort":"","getlistsortdir":"","sortconfig":"","gridpagesize":"","use_custom_prefix":"0","prefix":"","grid":"","gridload_mode":1,"check_resid":1,"check_resid_TV":"","join_alias":"","has_jointable":"yes","getlistwhere":"","joins":"","hooksnippets":"","cmpmaincaption":"","cmptabcaption":"","cmptabdescription":"","cmptabcontroller":"","winbuttons":"","onsubmitsuccess":"","submitparams":""},"permissions":{"apiaccess":"","view":"","list":"","save":"","create":"","remove":"","delete":"","publish":"","unpublish":"","viewdeleted":"","viewunpublished":""},"fieldpermissions":"","columns":"[{\"MIGX_id\":1,\"header\":\"\\u0421\\u043e\\u0434\\u0435\\u0440\\u0436\\u0438\\u043c\\u043e\\u0435\",\"dataIndex\":\"content\",\"width\":\"\",\"sortable\":\"false\",\"show_in_grid\":1,\"customrenderer\":\"\",\"renderer\":\"\",\"clickaction\":\"\",\"selectorconfig\":\"\",\"renderchunktpl\":\"\",\"renderoptions\":\"\",\"editor\":\"\"}]","createdby":1,"createdon":"2022-04-04 14:08:41","editedby":1,"editedon":"2022-04-04 19:50:16","deleted":0,"deletedon":null,"deletedby":0,"published":1,"publishedon":null,"publishedby":0,"category":""},{"id":6,"name":"list_triple_img","formtabs":"[{\"MIGX_id\":20,\"caption\":\"\",\"print_before_tabs\":\"0\",\"fields\":[{\"MIGX_id\":123,\"field\":\"title\",\"caption\":\"\\u0417\\u0430\\u0433\\u043e\\u043b\\u043e\\u0432\\u043e\\u043a\",\"description\":\"\\u043f\\u043e\\u044f\\u0432\\u043b\\u044f\\u0435\\u0442\\u0441\\u044f \\u043f\\u0440\\u0438 \\u043d\\u0430\\u0432\\u0435\\u0434\\u0435\\u043d\\u0438\\u0438\",\"description_is_code\":\"0\",\"inputTV\":\"\",\"inputTVtype\":\"\",\"validation\":\"\",\"configs\":\"\",\"restrictive_condition\":\"\",\"display\":\"\",\"sourceFrom\":\"config\",\"sources\":\"\",\"inputOptionValues\":\"\",\"default\":\"\",\"useDefaultIfEmpty\":\"0\",\"pos\":1},{\"MIGX_id\":124,\"field\":\"subtitle\",\"caption\":\"\\u041f\\u043e\\u0434\\u0437\\u0430\\u0433\\u043e\\u043b\\u043e\\u0432\\u043e\\u043a\",\"description\":\"\\u0438\\u0441\\u043f\\u043e\\u043b\\u044c\\u0437\\u0443\\u0435\\u0442\\u0441\\u044f \\u043d\\u0435 \\u0432\\u0441\\u0435\\u0433\\u0434\\u0430\",\"description_is_code\":\"0\",\"inputTV\":\"\",\"inputTVtype\":\"textarea\",\"validation\":\"\",\"configs\":\"\",\"restrictive_condition\":\"\",\"display\":\"\",\"sourceFrom\":\"config\",\"sources\":\"\",\"inputOptionValues\":\"\",\"default\":\"\",\"useDefaultIfEmpty\":\"0\",\"pos\":2},{\"MIGX_id\":125,\"field\":\"content\",\"caption\":\"\\u0421\\u043e\\u0434\\u0435\\u0440\\u0436\\u0438\\u043c\\u043e\\u0435\",\"description\":\"\\u043f\\u043e\\u044f\\u0432\\u043b\\u044f\\u0435\\u0442\\u0441\\u044f \\u0435\\u0441\\u043b\\u0438 \\u043a\\u0430\\u0440\\u0442\\u0438\\u043d\\u043a\\u0430 \\u043d\\u0435 \\u0437\\u0430\\u0433\\u0440\\u0443\\u0437\\u0438\\u043b\\u0430\\u0441\\u044c\",\"description_is_code\":\"0\",\"inputTV\":\"\",\"inputTVtype\":\"textarea\",\"validation\":\"\",\"configs\":\"\",\"restrictive_condition\":\"\",\"display\":\"\",\"sourceFrom\":\"config\",\"sources\":\"\",\"inputOptionValues\":\"\",\"default\":\"\",\"useDefaultIfEmpty\":\"0\",\"pos\":3},{\"MIGX_id\":126,\"field\":\"img\",\"caption\":\"\\u041a\\u0430\\u0440\\u0442\\u0438\\u043d\\u043a\\u0430\",\"description\":\"\",\"description_is_code\":\"0\",\"inputTV\":\"\",\"inputTVtype\":\"image\",\"validation\":\"\",\"configs\":\"\",\"restrictive_condition\":\"\",\"display\":\"\",\"sourceFrom\":\"config\",\"sources\":\"\",\"inputOptionValues\":\"\",\"default\":\"\",\"useDefaultIfEmpty\":\"0\",\"pos\":4},{\"MIGX_id\":127,\"field\":\"img_w\",\"caption\":\"\\u0428\\u0438\\u0440\\u0438\\u043d\\u0430\",\"description\":\"\\u0432 \\u043f\\u0438\\u043a\\u0441\\u0435\\u043b\\u044f\\u0445\",\"description_is_code\":\"0\",\"inputTV\":\"\",\"inputTVtype\":\"number\",\"validation\":\"\",\"configs\":\"\",\"restrictive_condition\":\"\",\"display\":\"\",\"sourceFrom\":\"config\",\"sources\":\"\",\"inputOptionValues\":\"\",\"default\":\"\",\"useDefaultIfEmpty\":\"0\",\"pos\":5},{\"MIGX_id\":128,\"field\":\"img_h\",\"caption\":\"\\u0412\\u044b\\u0441\\u043e\\u0442\\u0430\",\"description\":\"\\u0432 \\u043f\\u0438\\u043a\\u0441\\u0435\\u043b\\u044f\\u0445\",\"description_is_code\":\"0\",\"inputTV\":\"\",\"inputTVtype\":\"number\",\"validation\":\"\",\"configs\":\"\",\"restrictive_condition\":\"\",\"display\":\"\",\"sourceFrom\":\"config\",\"sources\":\"\",\"inputOptionValues\":\"\",\"default\":\"\",\"useDefaultIfEmpty\":\"0\",\"pos\":6},{\"MIGX_id\":129,\"field\":\"img_mob\",\"caption\":\"\\u041a\\u0430\\u0440\\u0442\\u0438\\u043d\\u043a\\u0430 \\u0434\\u043b\\u044f \\u043c\\u043e\\u0431\\u0438\\u043b\\u044c\\u043d\\u044b\\u0445\",\"description\":\"\",\"description_is_code\":\"0\",\"inputTV\":\"\",\"inputTVtype\":\"image\",\"validation\":\"\",\"configs\":\"\",\"restrictive_condition\":\"\",\"display\":\"\",\"sourceFrom\":\"config\",\"sources\":\"\",\"inputOptionValues\":\"\",\"default\":\"\",\"useDefaultIfEmpty\":\"0\",\"pos\":7},{\"MIGX_id\":130,\"field\":\"img_mob_w\",\"caption\":\"\\u0428\\u0438\\u0440\\u0438\\u043d\\u0430 \\u0434\\u043b\\u044f \\u043c\\u043e\\u0431\\u0438\\u043b\\u044c\\u043d\\u044b\\u0445\",\"description\":\"\\u0432 \\u043f\\u0438\\u043a\\u0441\\u0435\\u043b\\u044f\\u0445\",\"description_is_code\":\"0\",\"inputTV\":\"\",\"inputTVtype\":\"number\",\"validation\":\"\",\"configs\":\"\",\"restrictive_condition\":\"\",\"display\":\"\",\"sourceFrom\":\"config\",\"sources\":\"\",\"inputOptionValues\":\"\",\"default\":\"\",\"useDefaultIfEmpty\":\"0\",\"pos\":8},{\"MIGX_id\":131,\"field\":\"img_mob_h\",\"caption\":\"\\u0412\\u044b\\u0441\\u043e\\u0442\\u0430 \\u0434\\u043b\\u044f \\u043c\\u043e\\u0431\\u0438\\u043b\\u044c\\u043d\\u044b\\u0445\",\"description\":\"\\u0432 \\u043f\\u0438\\u043a\\u0441\\u0435\\u043b\\u044f\\u0445\",\"description_is_code\":\"0\",\"inputTV\":\"\",\"inputTVtype\":\"number\",\"validation\":\"\",\"configs\":\"\",\"restrictive_condition\":\"\",\"display\":\"\",\"sourceFrom\":\"config\",\"sources\":\"\",\"inputOptionValues\":\"\",\"default\":\"\",\"useDefaultIfEmpty\":\"0\",\"pos\":9}],\"pos\":1}]","contextmenus":"","actionbuttons":"","columnbuttons":"","filters":"","extended":{"migx_add":"","disable_add_item":"","add_items_directly":"","formcaption":"","update_win_title":"","win_id":"","maxRecords":"","addNewItemAt":"bottom","media_source_id":"","multiple_formtabs":"","multiple_formtabs_label":"","multiple_formtabs_field":"","multiple_formtabs_optionstext":"","multiple_formtabs_optionsvalue":"","actionbuttonsperrow":"4","winbuttonslist":"","extrahandlers":"","filtersperrow":"4","packageName":"","classname":"","task":"","getlistsort":"","getlistsortdir":"","sortconfig":"","gridpagesize":"","use_custom_prefix":"0","prefix":"","grid":"","gridload_mode":"1","check_resid":"1","check_resid_TV":"","join_alias":"","has_jointable":"yes","getlistwhere":"","joins":"","hooksnippets":"","cmpmaincaption":"","cmptabcaption":"","cmptabdescription":"","cmptabcontroller":"","winbuttons":"","onsubmitsuccess":"","submitparams":""},"permissions":{"apiaccess":"","view":"","list":"","save":"","create":"","remove":"","delete":"","publish":"","unpublish":"","viewdeleted":"","viewunpublished":""},"fieldpermissions":"","columns":"[{\"MIGX_id\":1,\"header\":\"\\u041a\\u0430\\u0440\\u0442\\u0438\\u043d\\u043a\\u0430\",\"dataIndex\":\"img\",\"width\":\"\",\"sortable\":\"false\",\"show_in_grid\":1,\"customrenderer\":\"\",\"renderer\":\"this.renderImage\",\"clickaction\":\"\",\"selectorconfig\":\"\",\"renderchunktpl\":\"\",\"renderoptions\":\"\",\"editor\":\"\"}]","createdby":1,"createdon":"2022-04-04 14:11:19","editedby":1,"editedon":"2022-10-02 13:49:35","deleted":0,"deletedon":null,"deletedby":0,"published":1,"publishedon":null,"publishedby":0,"category":""},{"id":7,"name":"contacts","formtabs":"[{\"MIGX_id\":40,\"caption\":\"\",\"print_before_tabs\":\"0\",\"fields\":[{\"MIGX_id\":252,\"field\":\"type\",\"caption\":\"\\u0422\\u0438\\u043f\",\"description\":\"\",\"description_is_code\":\"0\",\"inputTV\":\"\",\"inputTVtype\":\"listbox\",\"validation\":\"\",\"configs\":\"\",\"restrictive_condition\":\"\",\"display\":\"\",\"sourceFrom\":\"config\",\"sources\":\"\",\"inputOptionValues\":\"\\u0422\\u0435\\u043b\\u0435\\u0444\\u043e\\u043d==phone||Email==email||\\u0421\\u043e\\u0446.\\u0441\\u0435\\u0442\\u044c==social||\\u0410\\u0434\\u0440\\u0435\\u0441==address||\\u041a\\u0430\\u0440\\u0442\\u0430==map||\\u0412\\u0440\\u0435\\u043c\\u044f \\u0440\\u0430\\u0431\\u043e\\u0442\\u044b==worktime||\\u0420\\u0435\\u043a\\u0432\\u0438\\u0437\\u0438\\u0442==requisite\",\"default\":\"\",\"useDefaultIfEmpty\":\"0\",\"pos\":1},{\"MIGX_id\":253,\"field\":\"value\",\"caption\":\"\\u0417\\u043d\\u0430\\u0447\\u0435\\u043d\\u0438\\u0435\",\"description\":\"\",\"description_is_code\":\"0\",\"inputTV\":\"\",\"inputTVtype\":\"textarea\",\"validation\":\"\",\"configs\":\"\",\"restrictive_condition\":\"\",\"display\":\"\",\"sourceFrom\":\"config\",\"sources\":\"\",\"inputOptionValues\":\"\",\"default\":\"\",\"useDefaultIfEmpty\":\"0\",\"pos\":2},{\"MIGX_id\":254,\"field\":\"caption\",\"caption\":\"\\u041f\\u043e\\u0434\\u043f\\u0438\\u0441\\u044c\",\"description\":\"\",\"description_is_code\":\"0\",\"inputTV\":\"\",\"inputTVtype\":\"\",\"validation\":\"\",\"configs\":\"\",\"restrictive_condition\":\"\",\"display\":\"\",\"sourceFrom\":\"config\",\"sources\":\"\",\"inputOptionValues\":\"\",\"default\":\"\",\"useDefaultIfEmpty\":\"0\",\"pos\":3},{\"MIGX_id\":255,\"field\":\"icon_class\",\"caption\":\"\\u041a\\u043b\\u0430\\u0441\\u0441 \\u0438\\u043a\\u043e\\u043d\\u043a\\u0438\",\"description\":\"\",\"description_is_code\":\"0\",\"inputTV\":\"\",\"inputTVtype\":\"\",\"validation\":\"\",\"configs\":\"\",\"restrictive_condition\":\"\",\"display\":\"\",\"sourceFrom\":\"config\",\"sources\":\"\",\"inputOptionValues\":\"\",\"default\":\"\",\"useDefaultIfEmpty\":\"0\",\"pos\":4},{\"MIGX_id\":256,\"field\":\"form\",\"caption\":\"\\u041d\\u0430\\u0437\\u043d\\u0430\\u0447\\u0438\\u0442\\u044c \\u0444\\u043e\\u0440\\u043c\\u0435\",\"description\":\"\\u043f\\u043e\\u0437\\u0432\\u043e\\u043b\\u044f\\u0435\\u0442 \\u043f\\u0440\\u0438\\u0432\\u044f\\u0437\\u0430\\u0442\\u044c \\u043a\\u043e\\u043d\\u0442\\u0430\\u043a\\u0442 \\u043a  \\u043e\\u043f\\u0440\\u0435\\u0434\\u0435\\u043b\\u0435\\u043d\\u043d\\u043e\\u0439 \\u0444\\u043e\\u0440\\u043c\\u0435. \\u041d\\u0430\\u043f\\u0440\\u0438\\u043c\\u0435\\u0440, \\u0435\\u0441\\u043b\\u0438 \\u043f\\u0440\\u0438\\u0432\\u044f\\u0437\\u0430\\u0442\\u044c email, \\u0442\\u043e \\u043d\\u0430 \\u043d\\u0435\\u0433\\u043e \\u0431\\u0443\\u0434\\u0443\\u0442 \\u043e\\u0442\\u043f\\u0440\\u0430\\u0432\\u043b\\u044f\\u0442\\u044c\\u0441\\u044f \\u0434\\u0430\\u043d\\u043d\\u044b\\u0435 \\u0438\\u0437 \\u043f\\u0440\\u0438\\u0432\\u044f\\u0437\\u0430\\u043d\\u043d\\u043e\\u0439 \\u0444\\u043e\\u0440\\u043c\\u044b.\",\"description_is_code\":\"0\",\"inputTV\":\"\",\"inputTVtype\":\"listbox\",\"validation\":\"\",\"configs\":\"\",\"restrictive_condition\":\"\",\"display\":\"\",\"sourceFrom\":\"config\",\"sources\":\"\",\"inputOptionValues\":\"\\u041d\\u0435 \\u0432\\u044b\\u0431\\u0440\\u0430\\u043d||callback_print||callback_cmyk||callback\",\"default\":\"\",\"useDefaultIfEmpty\":\"0\",\"pos\":5},{\"MIGX_id\":280,\"field\":\"groups\",\"caption\":\"\\u0413\\u0440\\u0443\\u043f\\u043f\\u044b\",\"description\":\"\\u043c\\u043e\\u0436\\u043d\\u043e \\u0443\\u043a\\u0430\\u0437\\u0430\\u0442\\u044c \\u043d\\u0435\\u0441\\u043a\\u043e\\u043b\\u044c\\u043a\\u043e \\u0447\\u0435\\u0440\\u0435\\u0437 \\u0437\\u0430\\u043f\\u044f\\u0442\\u0443\\u044e\",\"description_is_code\":\"0\",\"inputTV\":\"\",\"inputTVtype\":\"\",\"validation\":\"\",\"configs\":\"\",\"restrictive_condition\":\"\",\"display\":\"\",\"sourceFrom\":\"config\",\"sources\":\"\",\"inputOptionValues\":\"\",\"default\":\"\",\"useDefaultIfEmpty\":\"0\",\"pos\":6}],\"pos\":1}]","contextmenus":"","actionbuttons":"","columnbuttons":"","filters":"","extended":{"migx_add":"","disable_add_item":"","add_items_directly":"","formcaption":"","update_win_title":"","win_id":"","maxRecords":"","addNewItemAt":"bottom","media_source_id":"","multiple_formtabs":"","multiple_formtabs_label":"","multiple_formtabs_field":"","multiple_formtabs_optionstext":"","multiple_formtabs_optionsvalue":"","actionbuttonsperrow":"4","winbuttonslist":"","extrahandlers":"","filtersperrow":"4","packageName":"","classname":"","task":"","getlistsort":"","getlistsortdir":"","sortconfig":"","gridpagesize":"","use_custom_prefix":"0","prefix":"","grid":"","gridload_mode":"1","check_resid":"1","check_resid_TV":"","join_alias":"","has_jointable":"yes","getlistwhere":"","joins":"","hooksnippets":"","cmpmaincaption":"","cmptabcaption":"","cmptabdescription":"","cmptabcontroller":"","winbuttons":"","onsubmitsuccess":"","submitparams":""},"permissions":{"apiaccess":"","view":"","list":"","save":"","create":"","remove":"","delete":"","publish":"","unpublish":"","viewdeleted":"","viewunpublished":""},"fieldpermissions":"","columns":"[{\"MIGX_id\":1,\"header\":\"\\u041f\\u043e\\u0434\\u043f\\u0438\\u0441\\u044c\",\"dataIndex\":\"caption\",\"width\":\"\",\"sortable\":\"false\",\"show_in_grid\":1,\"customrenderer\":\"\",\"renderer\":\"\",\"clickaction\":\"\",\"selectorconfig\":\"\",\"renderchunktpl\":\"\",\"renderoptions\":\"\",\"editor\":\"\"}]","createdby":1,"createdon":"2022-04-05 11:25:29","editedby":1,"editedon":"2023-11-04 13:07:30","deleted":0,"deletedon":null,"deletedby":0,"published":1,"publishedon":null,"publishedby":0,"category":""},{"id":8,"name":"form_list","formtabs":"[{\"MIGX_id\":22,\"caption\":\"\\u041d\\u0430\\u0441\\u0442\\u0440\\u043e\\u0439\\u043a\\u0438\",\"print_before_tabs\":\"0\",\"fields\":[{\"MIGX_id\":136,\"field\":\"fid\",\"caption\":\"ID \\u0444\\u043e\\u0440\\u043c\\u044b\",\"description\":\"\\u043f\\u043e \\u043d\\u0435\\u043c\\u0443 \\u043e\\u043f\\u0440\\u0435\\u0434\\u0435\\u043b\\u044f\\u0435\\u0442\\u0441\\u044f \\u0447\\u0430\\u043d\\u043a \\u0444\\u043e\\u0440\\u043c\\u044b\",\"description_is_code\":\"0\",\"inputTV\":\"\",\"inputTVtype\":\"listbox\",\"validation\":\"\",\"configs\":\"\",\"restrictive_condition\":\"\",\"display\":\"\",\"sourceFrom\":\"config\",\"sources\":\"\",\"inputOptionValues\":\"logout_form\",\"default\":\"\",\"useDefaultIfEmpty\":\"0\",\"pos\":1},{\"MIGX_id\":137,\"field\":\"formName\",\"caption\":\"\\u041d\\u0430\\u0437\\u0432\\u0430\\u043d\\u0438\\u0435 \\u0444\\u043e\\u0440\\u043c\\u044b\",\"description\":\"\",\"description_is_code\":\"0\",\"inputTV\":\"\",\"inputTVtype\":\"\",\"validation\":\"\",\"configs\":\"\",\"restrictive_condition\":\"\",\"display\":\"\",\"sourceFrom\":\"config\",\"sources\":\"\",\"inputOptionValues\":\"\",\"default\":\"\",\"useDefaultIfEmpty\":\"0\",\"pos\":2}],\"pos\":1},{\"MIGX_id\":23,\"caption\":\"\\u041f\\u0430\\u0440\\u0430\\u043c\\u0435\\u0442\\u0440\\u044b\",\"print_before_tabs\":\"0\",\"fields\":[{\"MIGX_id\":138,\"field\":\"params\",\"caption\":\"\\u0421\\u043f\\u0438\\u0441\\u043e\\u043a \\u043f\\u0430\\u0440\\u0430\\u043c\\u0435\\u0442\\u0440\\u043e\\u0432\",\"description\":\"\\u044d\\u0442\\u0438 \\u043f\\u0430\\u0440\\u0430\\u043c\\u0435\\u0442\\u0440\\u044b \\u043f\\u0435\\u0440\\u0435\\u043e\\u043f\\u0440\\u0435\\u0434\\u0435\\u043b\\u044f\\u0442 \\u043e\\u0434\\u043d\\u043e\\u0438\\u043c\\u0435\\u043d\\u043d\\u044b\\u0435 \\u043f\\u0430\\u0440\\u0430\\u043c\\u0435\\u0442\\u0440\\u044b \\u0438\\u0437 \\u043f\\u0440\\u0435\\u0441\\u0435\\u0442\\u0430\",\"description_is_code\":\"0\",\"inputTV\":\"\",\"inputTVtype\":\"migx\",\"validation\":\"\",\"configs\":\"list_double\",\"restrictive_condition\":\"\",\"display\":\"\",\"sourceFrom\":\"config\",\"sources\":\"\",\"inputOptionValues\":\"\",\"default\":\"\",\"useDefaultIfEmpty\":\"0\",\"pos\":1},{\"MIGX_id\":139,\"field\":\"preset\",\"caption\":\"\\u041f\\u0440\\u0435\\u0441\\u0435\\u0442\",\"description\":\"\\u0431\\u0435\\u0440\\u0443\\u0442\\u0441\\u044f \\u0438\\u0437 \\u0444\\u0430\\u0439\\u043b\\u0430 core\\\/elements\\\/presets\\\/ajaxform.json\",\"description_is_code\":\"0\",\"inputTV\":\"\",\"inputTVtype\":\"listbox\",\"validation\":\"\",\"configs\":\"\",\"restrictive_condition\":\"\",\"display\":\"\",\"sourceFrom\":\"config\",\"sources\":\"\",\"inputOptionValues\":\"\\u041d\\u0435 \\u0432\\u044b\\u0431\\u0440\\u0430\\u043d||login_form||register_form||reset_form||logout_form||callback_form\",\"default\":\"\",\"useDefaultIfEmpty\":\"0\",\"pos\":2}],\"pos\":2}]","contextmenus":"","actionbuttons":"","columnbuttons":"","filters":"","extended":{"migx_add":"","disable_add_item":"","add_items_directly":"","formcaption":"","update_win_title":"","win_id":"","maxRecords":"","addNewItemAt":"bottom","media_source_id":"","multiple_formtabs":"","multiple_formtabs_label":"","multiple_formtabs_field":"","multiple_formtabs_optionstext":"","multiple_formtabs_optionsvalue":"","actionbuttonsperrow":4,"winbuttonslist":"","extrahandlers":"","filtersperrow":4,"packageName":"","classname":"","task":"","getlistsort":"","getlistsortdir":"","sortconfig":"","gridpagesize":"","use_custom_prefix":"0","prefix":"","grid":"","gridload_mode":1,"check_resid":1,"check_resid_TV":"","join_alias":"","has_jointable":"yes","getlistwhere":"","joins":"","hooksnippets":"","cmpmaincaption":"","cmptabcaption":"","cmptabdescription":"","cmptabcontroller":"","winbuttons":"","onsubmitsuccess":"","submitparams":""},"permissions":{"apiaccess":"","view":"","list":"","save":"","create":"","remove":"","delete":"","publish":"","unpublish":"","viewdeleted":"","viewunpublished":""},"fieldpermissions":"","columns":"[{\"MIGX_id\":1,\"header\":\"\\u041d\\u0430\\u0437\\u0432\\u0430\\u043d\\u0438\\u0435 \\u0444\\u043e\\u0440\\u043c\\u044b\",\"dataIndex\":\"formName\",\"width\":\"\",\"sortable\":\"false\",\"show_in_grid\":1,\"customrenderer\":\"\",\"renderer\":\"\",\"clickaction\":\"\",\"selectorconfig\":\"\",\"renderchunktpl\":\"\",\"renderoptions\":\"\",\"editor\":\"\"}]","createdby":1,"createdon":"2022-04-05 21:27:56","editedby":1,"editedon":"2022-08-22 15:41:03","deleted":0,"deletedon":null,"deletedby":0,"published":1,"publishedon":null,"publishedby":0,"category":""},{"id":9,"name":"list_double_img","formtabs":"[{\"MIGX_id\":24,\"caption\":\"\",\"print_before_tabs\":\"0\",\"fields\":[{\"MIGX_id\":140,\"field\":\"title\",\"caption\":\"\\u0417\\u0430\\u0433\\u043e\\u043b\\u043e\\u0432\\u043e\\u043a\",\"description\":\"\\u043f\\u043e\\u044f\\u0432\\u043b\\u044f\\u0435\\u0442\\u0441\\u044f \\u043f\\u0440\\u0438 \\u043d\\u0430\\u0432\\u0435\\u0434\\u0435\\u043d\\u0438\\u0438\",\"description_is_code\":\"0\",\"inputTV\":\"\",\"inputTVtype\":\"\",\"validation\":\"\",\"configs\":\"\",\"restrictive_condition\":\"\",\"display\":\"\",\"sourceFrom\":\"config\",\"sources\":\"\",\"inputOptionValues\":\"\",\"default\":\"\",\"useDefaultIfEmpty\":\"0\",\"pos\":1},{\"MIGX_id\":141,\"field\":\"content\",\"caption\":\"\\u0421\\u043e\\u0434\\u0435\\u0440\\u0436\\u0438\\u043c\\u043e\\u0435\",\"description\":\"\\u043f\\u043e\\u044f\\u0432\\u043b\\u044f\\u0435\\u0442\\u0441\\u044f \\u0435\\u0441\\u043b\\u0438 \\u043a\\u0430\\u0440\\u0442\\u0438\\u043d\\u043a\\u0430 \\u043d\\u0435 \\u0437\\u0430\\u0433\\u0440\\u0443\\u0437\\u0438\\u043b\\u0430\\u0441\\u044c\",\"description_is_code\":\"0\",\"inputTV\":\"\",\"inputTVtype\":\"textarea\",\"validation\":\"\",\"configs\":\"\",\"restrictive_condition\":\"\",\"display\":\"\",\"sourceFrom\":\"config\",\"sources\":\"\",\"inputOptionValues\":\"\",\"default\":\"\",\"useDefaultIfEmpty\":\"0\",\"pos\":2},{\"MIGX_id\":142,\"field\":\"img\",\"caption\":\"\\u041a\\u0430\\u0440\\u0442\\u0438\\u043d\\u043a\\u0430\",\"description\":\"\",\"description_is_code\":\"0\",\"inputTV\":\"\",\"inputTVtype\":\"image\",\"validation\":\"\",\"configs\":\"\",\"restrictive_condition\":\"\",\"display\":\"\",\"sourceFrom\":\"config\",\"sources\":\"\",\"inputOptionValues\":\"\",\"default\":\"\",\"useDefaultIfEmpty\":\"0\",\"pos\":3},{\"MIGX_id\":143,\"field\":\"img_w\",\"caption\":\"\\u0428\\u0438\\u0440\\u0438\\u043d\\u0430\",\"description\":\"\\u0432 \\u043f\\u0438\\u043a\\u0441\\u0435\\u043b\\u044f\\u0445\",\"description_is_code\":\"0\",\"inputTV\":\"\",\"inputTVtype\":\"number\",\"validation\":\"\",\"configs\":\"\",\"restrictive_condition\":\"\",\"display\":\"\",\"sourceFrom\":\"config\",\"sources\":\"\",\"inputOptionValues\":\"\",\"default\":\"\",\"useDefaultIfEmpty\":\"0\",\"pos\":4},{\"MIGX_id\":144,\"field\":\"img_h\",\"caption\":\"\\u0412\\u044b\\u0441\\u043e\\u0442\\u0430\",\"description\":\"\\u0432 \\u043f\\u0438\\u043a\\u0441\\u0435\\u043b\\u044f\\u0445\",\"description_is_code\":\"0\",\"inputTV\":\"\",\"inputTVtype\":\"number\",\"validation\":\"\",\"configs\":\"\",\"restrictive_condition\":\"\",\"display\":\"\",\"sourceFrom\":\"config\",\"sources\":\"\",\"inputOptionValues\":\"\",\"default\":\"\",\"useDefaultIfEmpty\":\"0\",\"pos\":5},{\"MIGX_id\":145,\"field\":\"img_mob\",\"caption\":\"\\u041a\\u0430\\u0440\\u0442\\u0438\\u043d\\u043a\\u0430 \\u0434\\u043b\\u044f \\u043c\\u043e\\u0431\\u0438\\u043b\\u044c\\u043d\\u044b\\u0445\",\"description\":\"\",\"description_is_code\":\"0\",\"inputTV\":\"\",\"inputTVtype\":\"image\",\"validation\":\"\",\"configs\":\"\",\"restrictive_condition\":\"\",\"display\":\"\",\"sourceFrom\":\"config\",\"sources\":\"\",\"inputOptionValues\":\"\",\"default\":\"\",\"useDefaultIfEmpty\":\"0\",\"pos\":6},{\"MIGX_id\":146,\"field\":\"img_mob_w\",\"caption\":\"\\u0428\\u0438\\u0440\\u0438\\u043d\\u0430 \\u0434\\u043b\\u044f \\u043c\\u043e\\u0431\\u0438\\u043b\\u044c\\u043d\\u044b\\u0445\",\"description\":\"\\u0432 \\u043f\\u0438\\u043a\\u0441\\u0435\\u043b\\u044f\\u0445\",\"description_is_code\":\"0\",\"inputTV\":\"\",\"inputTVtype\":\"number\",\"validation\":\"\",\"configs\":\"\",\"restrictive_condition\":\"\",\"display\":\"\",\"sourceFrom\":\"config\",\"sources\":\"\",\"inputOptionValues\":\"\",\"default\":\"\",\"useDefaultIfEmpty\":\"0\",\"pos\":7},{\"MIGX_id\":147,\"field\":\"img_mob_h\",\"caption\":\"\\u0412\\u044b\\u0441\\u043e\\u0442\\u0430 \\u0434\\u043b\\u044f \\u043c\\u043e\\u0431\\u0438\\u043b\\u044c\\u043d\\u044b\\u0445\",\"description\":\"\\u0432 \\u043f\\u0438\\u043a\\u0441\\u0435\\u043b\\u044f\\u0445\",\"description_is_code\":\"0\",\"inputTV\":\"\",\"inputTVtype\":\"number\",\"validation\":\"\",\"configs\":\"\",\"restrictive_condition\":\"\",\"display\":\"\",\"sourceFrom\":\"config\",\"sources\":\"\",\"inputOptionValues\":\"\",\"default\":\"\",\"useDefaultIfEmpty\":\"0\",\"pos\":8}],\"pos\":1}]","contextmenus":"","actionbuttons":"","columnbuttons":"","filters":"","extended":{"migx_add":"","disable_add_item":"","add_items_directly":"","formcaption":"","update_win_title":"","win_id":"","maxRecords":"","addNewItemAt":"bottom","media_source_id":"","multiple_formtabs":"","multiple_formtabs_label":"","multiple_formtabs_field":"","multiple_formtabs_optionstext":"","multiple_formtabs_optionsvalue":"","actionbuttonsperrow":"4","winbuttonslist":"","extrahandlers":"","filtersperrow":"4","packageName":"","classname":"","task":"","getlistsort":"","getlistsortdir":"","sortconfig":"","gridpagesize":"","use_custom_prefix":"0","prefix":"","grid":"","gridload_mode":"1","check_resid":"1","check_resid_TV":"","join_alias":"","has_jointable":"yes","getlistwhere":"","joins":"","hooksnippets":"","cmpmaincaption":"","cmptabcaption":"","cmptabdescription":"","cmptabcontroller":"","winbuttons":"","onsubmitsuccess":"","submitparams":""},"permissions":{"apiaccess":"","view":"","list":"","save":"","create":"","remove":"","delete":"","publish":"","unpublish":"","viewdeleted":"","viewunpublished":""},"fieldpermissions":"","columns":"[{\"MIGX_id\":1,\"header\":\"\\u041a\\u0430\\u0440\\u0442\\u0438\\u043d\\u043a\\u0430\",\"dataIndex\":\"img\",\"width\":\"\",\"sortable\":\"false\",\"show_in_grid\":1,\"customrenderer\":\"\",\"renderer\":\"this.renderImage\",\"clickaction\":\"\",\"selectorconfig\":\"\",\"renderchunktpl\":\"\",\"renderoptions\":\"\",\"editor\":\"\"}]","createdby":1,"createdon":"2022-09-30 11:55:27","editedby":1,"editedon":"2022-10-02 13:50:13","deleted":0,"deletedon":null,"deletedby":0,"published":1,"publishedon":null,"publishedby":0,"category":""},{"id":10,"name":"list_simple_img","formtabs":"[{\"MIGX_id\":25,\"caption\":\"\",\"print_before_tabs\":\"0\",\"fields\":[{\"MIGX_id\":148,\"field\":\"title\",\"caption\":\"\\u0417\\u0430\\u0433\\u043e\\u043b\\u043e\\u0432\\u043e\\u043a\",\"description\":\"\\u043f\\u043e\\u044f\\u0432\\u043b\\u044f\\u0435\\u0442\\u0441\\u044f \\u043f\\u0440\\u0438 \\u043d\\u0430\\u0432\\u0435\\u0434\\u0435\\u043d\\u0438\\u0438\",\"description_is_code\":\"0\",\"inputTV\":\"\",\"inputTVtype\":\"\",\"validation\":\"\",\"configs\":\"\",\"restrictive_condition\":\"\",\"display\":\"\",\"sourceFrom\":\"config\",\"sources\":\"\",\"inputOptionValues\":\"\",\"default\":\"\",\"useDefaultIfEmpty\":\"0\",\"pos\":1},{\"MIGX_id\":149,\"field\":\"img\",\"caption\":\"\\u041a\\u0430\\u0440\\u0442\\u0438\\u043d\\u043a\\u0430\",\"description\":\"\",\"description_is_code\":\"0\",\"inputTV\":\"\",\"inputTVtype\":\"image\",\"validation\":\"\",\"configs\":\"\",\"restrictive_condition\":\"\",\"display\":\"\",\"sourceFrom\":\"config\",\"sources\":\"\",\"inputOptionValues\":\"\",\"default\":\"\",\"useDefaultIfEmpty\":\"0\",\"pos\":2},{\"MIGX_id\":150,\"field\":\"img_w\",\"caption\":\"\\u0428\\u0438\\u0440\\u0438\\u043d\\u0430\",\"description\":\"\\u0432 \\u043f\\u0438\\u043a\\u0441\\u0435\\u043b\\u044f\\u0445\",\"description_is_code\":\"0\",\"inputTV\":\"\",\"inputTVtype\":\"number\",\"validation\":\"\",\"configs\":\"\",\"restrictive_condition\":\"\",\"display\":\"\",\"sourceFrom\":\"config\",\"sources\":\"\",\"inputOptionValues\":\"\",\"default\":\"\",\"useDefaultIfEmpty\":\"0\",\"pos\":3},{\"MIGX_id\":151,\"field\":\"img_h\",\"caption\":\"\\u0412\\u044b\\u0441\\u043e\\u0442\\u0430\",\"description\":\"\\u0432 \\u043f\\u0438\\u043a\\u0441\\u0435\\u043b\\u044f\\u0445\",\"description_is_code\":\"0\",\"inputTV\":\"\",\"inputTVtype\":\"number\",\"validation\":\"\",\"configs\":\"\",\"restrictive_condition\":\"\",\"display\":\"\",\"sourceFrom\":\"config\",\"sources\":\"\",\"inputOptionValues\":\"\",\"default\":\"\",\"useDefaultIfEmpty\":\"0\",\"pos\":4},{\"MIGX_id\":152,\"field\":\"img_mob\",\"caption\":\"\\u041a\\u0430\\u0440\\u0442\\u0438\\u043d\\u043a\\u0430 \\u0434\\u043b\\u044f \\u043c\\u043e\\u0431\\u0438\\u043b\\u044c\\u043d\\u044b\\u0445\",\"description\":\"\",\"description_is_code\":\"0\",\"inputTV\":\"\",\"inputTVtype\":\"image\",\"validation\":\"\",\"configs\":\"\",\"restrictive_condition\":\"\",\"display\":\"\",\"sourceFrom\":\"config\",\"sources\":\"\",\"inputOptionValues\":\"\",\"default\":\"\",\"useDefaultIfEmpty\":\"0\",\"pos\":5},{\"MIGX_id\":153,\"field\":\"img_mob_w\",\"caption\":\"\\u0428\\u0438\\u0440\\u0438\\u043d\\u0430 \\u0434\\u043b\\u044f \\u043c\\u043e\\u0431\\u0438\\u043b\\u044c\\u043d\\u044b\\u0445\",\"description\":\"\\u0432 \\u043f\\u0438\\u043a\\u0441\\u0435\\u043b\\u044f\\u0445\",\"description_is_code\":\"0\",\"inputTV\":\"\",\"inputTVtype\":\"number\",\"validation\":\"\",\"configs\":\"\",\"restrictive_condition\":\"\",\"display\":\"\",\"sourceFrom\":\"config\",\"sources\":\"\",\"inputOptionValues\":\"\",\"default\":\"\",\"useDefaultIfEmpty\":\"0\",\"pos\":6},{\"MIGX_id\":154,\"field\":\"img_mob_h\",\"caption\":\"\\u0412\\u044b\\u0441\\u043e\\u0442\\u0430 \\u0434\\u043b\\u044f \\u043c\\u043e\\u0431\\u0438\\u043b\\u044c\\u043d\\u044b\\u0445\",\"description\":\"\\u0432 \\u043f\\u0438\\u043a\\u0441\\u0435\\u043b\\u044f\\u0445\",\"description_is_code\":\"0\",\"inputTV\":\"\",\"inputTVtype\":\"number\",\"validation\":\"\",\"configs\":\"\",\"restrictive_condition\":\"\",\"display\":\"\",\"sourceFrom\":\"config\",\"sources\":\"\",\"inputOptionValues\":\"\",\"default\":\"\",\"useDefaultIfEmpty\":\"0\",\"pos\":7}],\"pos\":1}]","contextmenus":"","actionbuttons":"","columnbuttons":"","filters":"","extended":{"migx_add":"","disable_add_item":"","add_items_directly":"","formcaption":"","update_win_title":"","win_id":"","maxRecords":"","addNewItemAt":"bottom","media_source_id":"","multiple_formtabs":"","multiple_formtabs_label":"","multiple_formtabs_field":"","multiple_formtabs_optionstext":"","multiple_formtabs_optionsvalue":"","actionbuttonsperrow":"4","winbuttonslist":"","extrahandlers":"","filtersperrow":"4","packageName":"","classname":"","task":"","getlistsort":"","getlistsortdir":"","sortconfig":"","gridpagesize":"","use_custom_prefix":"0","prefix":"","grid":"","gridload_mode":"1","check_resid":"1","check_resid_TV":"","join_alias":"","has_jointable":"yes","getlistwhere":"","joins":"","hooksnippets":"","cmpmaincaption":"","cmptabcaption":"","cmptabdescription":"","cmptabcontroller":"","winbuttons":"","onsubmitsuccess":"","submitparams":""},"permissions":{"apiaccess":"","view":"","list":"","save":"","create":"","remove":"","delete":"","publish":"","unpublish":"","viewdeleted":"","viewunpublished":""},"fieldpermissions":"","columns":"[{\"MIGX_id\":1,\"header\":\"\\u041a\\u0430\\u0440\\u0442\\u0438\\u043d\\u043a\\u0430\",\"dataIndex\":\"img\",\"width\":\"\",\"sortable\":\"false\",\"show_in_grid\":1,\"customrenderer\":\"\",\"renderer\":\"this.renderImage\",\"clickaction\":\"\",\"selectorconfig\":\"\",\"renderchunktpl\":\"\",\"renderoptions\":\"\",\"editor\":\"\"}]","createdby":1,"createdon":"2022-09-30 11:55:40","editedby":1,"editedon":"2022-10-02 13:51:02","deleted":0,"deletedon":null,"deletedby":0,"published":1,"publishedon":null,"publishedby":0,"category":""},{"id":11,"name":"list_of_lists","formtabs":"[{\"MIGX_id\":31,\"caption\":\"\",\"print_before_tabs\":\"0\",\"fields\":[{\"MIGX_id\":203,\"field\":\"list_triple_img\",\"caption\":\"\\u0422\\u0440\\u043e\\u0439\\u043d\\u043e\\u0439 \\u0441\\u043f\\u0438\\u0441\\u043e\\u043a \\u0441 \\u043a\\u0430\\u0440\\u0442\\u0438\\u043d\\u043a\\u043e\\u0439\",\"description\":\"\",\"description_is_code\":\"0\",\"inputTV\":\"\",\"inputTVtype\":\"migx\",\"validation\":\"\",\"configs\":\"list_triple_img\",\"restrictive_condition\":\"\",\"display\":\"\",\"sourceFrom\":\"config\",\"sources\":\"\",\"inputOptionValues\":\"\",\"default\":\"\",\"useDefaultIfEmpty\":\"0\",\"pos\":1},{\"MIGX_id\":204,\"field\":\"title\",\"caption\":\"\\u0417\\u0430\\u0433\\u043e\\u043b\\u043e\\u0432\\u043e\\u043a\",\"description\":\"\",\"description_is_code\":\"0\",\"inputTV\":\"\",\"inputTVtype\":\"\",\"validation\":\"\",\"configs\":\"\",\"restrictive_condition\":\"\",\"display\":\"\",\"sourceFrom\":\"config\",\"sources\":\"\",\"inputOptionValues\":\"\",\"default\":\"\",\"useDefaultIfEmpty\":\"0\",\"pos\":2},{\"MIGX_id\":205,\"field\":\"block_id\",\"caption\":\"ID \\u0431\\u043b\\u043e\\u043a\\u0430\",\"description\":\"\",\"description_is_code\":\"0\",\"inputTV\":\"\",\"inputTVtype\":\"\",\"validation\":\"\",\"configs\":\"\",\"restrictive_condition\":\"\",\"display\":\"\",\"sourceFrom\":\"config\",\"sources\":\"\",\"inputOptionValues\":\"\",\"default\":\"\",\"useDefaultIfEmpty\":\"0\",\"pos\":3}],\"pos\":1}]","contextmenus":"","actionbuttons":"","columnbuttons":"","filters":"","extended":{"migx_add":"","disable_add_item":"","add_items_directly":"","formcaption":"","update_win_title":"","win_id":"","maxRecords":"","addNewItemAt":"bottom","media_source_id":"","multiple_formtabs":"","multiple_formtabs_label":"","multiple_formtabs_field":"","multiple_formtabs_optionstext":"","multiple_formtabs_optionsvalue":"","actionbuttonsperrow":"4","winbuttonslist":"","extrahandlers":"","filtersperrow":"4","packageName":"","classname":"","task":"","getlistsort":"","getlistsortdir":"","sortconfig":"","gridpagesize":"","use_custom_prefix":"0","prefix":"","grid":"","gridload_mode":"1","check_resid":"1","check_resid_TV":"","join_alias":"","has_jointable":"yes","getlistwhere":"","joins":"","hooksnippets":"","cmpmaincaption":"","cmptabcaption":"","cmptabdescription":"","cmptabcontroller":"","winbuttons":"","onsubmitsuccess":"","submitparams":""},"permissions":{"apiaccess":"","view":"","list":"","save":"","create":"","remove":"","delete":"","publish":"","unpublish":"","viewdeleted":"","viewunpublished":""},"fieldpermissions":"","columns":"[{\"MIGX_id\":1,\"header\":\"\\u0417\\u0430\\u0433\\u043e\\u043b\\u043e\\u0432\\u043e\\u043a\",\"dataIndex\":\"title\",\"width\":\"\",\"sortable\":\"false\",\"show_in_grid\":1,\"customrenderer\":\"\",\"renderer\":\"\",\"clickaction\":\"\",\"selectorconfig\":\"\",\"renderchunktpl\":\"\",\"renderoptions\":\"\",\"editor\":\"\"}]","createdby":1,"createdon":"2022-10-03 10:45:10","editedby":1,"editedon":"2023-04-17 16:41:41","deleted":0,"deletedon":null,"deletedby":0,"published":1,"publishedon":null,"publishedby":0,"category":""}]